selve/__init__.py
selve/iveo.py
selve/protocol.py
selve/utils.py
python_selve-1.4.1.dist-info/LICENSE
python_selve-1.4.1.dist-info/METADATA
python_selve-1.4.1.dist-info/WHEEL
python_selve-1.4.1.dist-info/top_level.txt
python_selve-1.4.1.dist-info/RECORD
