Metadata-Version: 2.1
Name: python-selve
Version: 1.4.1
Summary: Python library for interfacing with selve devices using the USB-RF controller
Home-page: https://github.com/gpulido/python-selve
Author: Gabriel Pulido
Author-email: gabriel.pulidodetorres@gmail.com
Keywords: selve blind awning shutter usb rf
Classifier: Development Status :: 3 - Alpha
Classifier: Intended Audience :: Developers
Classifier: Topic :: Software Development :: Build Tools
Classifier: License :: OSI Approved :: MIT License
Classifier: Programming Language :: Python :: 3
Classifier: Programming Language :: Python :: 3.4
Classifier: Programming Language :: Python :: 3.5
Classifier: Programming Language :: Python :: 3.6
License-File: LICENSE
Requires-Dist: pySerial
Requires-Dist: pybase64
Requires-Dist: untangle
